odoo/addons/procurement_mto_analytic/README.rst
odoo/addons/procurement_mto_analytic/__init__.py
odoo/addons/procurement_mto_analytic/__manifest__.py
odoo/addons/procurement_mto_analytic/i18n/ca.po
odoo/addons/procurement_mto_analytic/i18n/es.po
odoo/addons/procurement_mto_analytic/i18n/procurement_mto_analytic.pot
odoo/addons/procurement_mto_analytic/i18n/purchase_procurement_analytic.pot
odoo/addons/procurement_mto_analytic/models/__init__.py
odoo/addons/procurement_mto_analytic/models/purchase_order_line.py
odoo/addons/procurement_mto_analytic/models/sale_order_line.py
odoo/addons/procurement_mto_analytic/models/stock_move.py
odoo/addons/procurement_mto_analytic/models/stock_rule.py
odoo/addons/procurement_mto_analytic/readme/CONTRIBUTORS.rst
odoo/addons/procurement_mto_analytic/readme/DESCRIPTION.rst
odoo/addons/procurement_mto_analytic/readme/HISTORY.rst
odoo/addons/procurement_mto_analytic/readme/USAGE.rst
odoo/addons/procurement_mto_analytic/static/description/icon.png
odoo/addons/procurement_mto_analytic/static/description/index.html
odoo/addons/procurement_mto_analytic/tests/__init__.py
odoo/addons/procurement_mto_analytic/tests/test_purchase_procurement_analytic.py
odoo_addon_procurement_mto_analytic-15.0.1.0.0.6.dist-info/METADATA
odoo_addon_procurement_mto_analytic-15.0.1.0.0.6.dist-info/WHEEL
odoo_addon_procurement_mto_analytic-15.0.1.0.0.6.dist-info/top_level.txt
odoo_addon_procurement_mto_analytic-15.0.1.0.0.6.dist-info/RECORD
