Metadata-Version: 2.1
Name: odoo-addon-procurement_mto_analytic
Version: 15.0.1.0.0.6
Summary: This module sets analytic account in purchase order line from sale order analytic account
Home-page: https://github.com/OCA/account-analytic
Author: Tecnativa, VentorTech, Odoo Community Association (OCA)
Author-email: support@odoo-community.org
License: AGPL-3
Classifier: Programming Language :: Python
Classifier: Framework :: Odoo
Classifier: Framework :: Odoo :: 15.0
Classifier: License :: OSI Approved :: GNU Affero General Public License v3
Requires-Python: >=3.8
Requires-Dist: odoo <15.1dev,>=15.0a
